examples/__init__.py
examples/example_corpus.py
examples/liwc.py
examples/ner.py
examples/pos.py
examples/syntax.py
examples/textstats.py
examples/word_embeds.py
nlpkit/__init__.py
nlpkit/nlp_feature_extraction/__init__.py
nlpkit/nlp_feature_extraction/liwc_features.py
nlpkit/nlp_feature_extraction/ner_features.py
nlpkit/nlp_feature_extraction/pos_features.py
nlpkit/nlp_feature_extraction/syntax_features.py
nlpkit/nlp_feature_extraction/text_statistics_features.py
nlpkit/nlp_feature_extraction/word_embeddings_features.py
nlpkit/nlp_feature_extraction/liwc/__init__.py
nlpkit/nlp_feature_extraction/liwc/liwc.py
nlpkit/nlp_feature_extraction/liwc/test_liwc.py
nlpkit/nlp_feature_extraction/tests/__init__.py
nlpkit/nlp_feature_extraction/tests/test_liwc_feature_extraction.py
nlpkit/nlp_feature_extraction/tests/test_ner_feature_extraction.py
nlpkit/nlp_feature_extraction/tests/test_pos_feature_extraction.py
nlpkit/nlp_feature_extraction/tests/test_syntax_feature_extraction.py
nlpkit/nlp_feature_extraction/tests/test_word_embeddings_feature_extraction.py
nlpkit_ml-1.0.0.dist-info/LICENSE
nlpkit_ml-1.0.0.dist-info/METADATA
nlpkit_ml-1.0.0.dist-info/WHEEL
nlpkit_ml-1.0.0.dist-info/top_level.txt
nlpkit_ml-1.0.0.dist-info/RECORD
