Metadata-Version: 2.1
Name: nlpkit-ml
Version: 1.0.0
Summary: A library of scikit compatible text transformers, that are ready to be integrated in an NLP pipeline for various classification tasks.
Home-page: https://github.com/evanll/nlpkit-ml
Author: Evan Lalopoulos
Author-email: evan.lalopoulos.2017@my.bristol.ac.uk
License: UNKNOWN
Platform: UNKNOWN
Classifier: Programming Language :: Python :: 3
Classifier: Operating System :: OS Independent
Requires-Python: >=3.6
Requires-Dist: Pyphen (==0.9.5)
Requires-Dist: atomicwrites (==1.3.0)
Requires-Dist: attrs (==19.1.0)
Requires-Dist: boto3 (==1.9.220)
Requires-Dist: boto (==2.49.0)
Requires-Dist: botocore (==1.12.220)
Requires-Dist: certifi (==2019.6.16)
Requires-Dist: chardet (==3.0.4)
Requires-Dist: docutils (==0.15.2)
Requires-Dist: gensim (==3.4.0)
Requires-Dist: idna (==2.8)
Requires-Dist: importlib-metadata (==0.19)
Requires-Dist: jmespath (==0.9.4)
Requires-Dist: more-itertools (==7.2.0)
Requires-Dist: nltk (==3.4.5)
Requires-Dist: numpy (==1.14.5)
Requires-Dist: packaging (==19.1)
Requires-Dist: pluggy (==0.12.0)
Requires-Dist: py (==1.8.0)
Requires-Dist: pyparsing (==2.4.2)
Requires-Dist: pytest (==5.1.2)
Requires-Dist: python-dateutil (==2.8.0)
Requires-Dist: repoze.lru (==0.7)
Requires-Dist: requests (==2.22.0)
Requires-Dist: s3transfer (==0.2.1)
Requires-Dist: scikit-learn (==0.19.1)
Requires-Dist: scipy (==1.1.0)
Requires-Dist: six (==1.12.0)
Requires-Dist: smart-open (==1.8.4)
Requires-Dist: textstat (==0.4.1)
Requires-Dist: urllib3 (==1.25.3)
Requires-Dist: wcwidth (==0.1.7)
Requires-Dist: zipp (==0.6.0)
